ppc/__init__.py
ppc/__main__.py
ppc/python_project_creator.py
neps-0.0.1.dist-info/LICENSE
neps-0.0.1.dist-info/METADATA
neps-0.0.1.dist-info/WHEEL
neps-0.0.1.dist-info/entry_points.txt
neps-0.0.1.dist-info/top_level.txt
neps-0.0.1.dist-info/RECORD
