Metadata-Version: 2.1
Name: neps
Version: 0.0.1
Summary: This is a placeholder for Neps Academy
Home-page: https://github.com/ThiNepo
Author: Thiago Nepomuceno
Author-email: thi.nepo@gmail.com
License: UNKNOWN
Platform: UNKNOWN
Classifier: Programming Language :: Python :: 3
Classifier: License :: OSI Approved :: MIT License
Classifier: Operating System :: OS Independent
License-File: LICENSE
Requires-Dist: toml
Requires-Dist: click
